ci_jira_releaser/__init__.py
ci_jira_releaser-0.3.8.7.data/scripts/ci-jira-releaser
ci_jira_releaser-0.3.8.7.dist-info/DESCRIPTION.rst
ci_jira_releaser-0.3.8.7.dist-info/METADATA
ci_jira_releaser-0.3.8.7.dist-info/RECORD
ci_jira_releaser-0.3.8.7.dist-info/WHEEL
ci_jira_releaser-0.3.8.7.dist-info/metadata.json
ci_jira_releaser-0.3.8.7.dist-info/top_level.txt
