Metadata-Version: 2.0
Name: ci-jira-releaser
Version: 0.3.8.7
Summary: Simple way to release past(or current) commits within Jira
Home-page: https://github.com/bookmd/jira-releaser
Author: Ben Waters
Author-email: ben@book-md.com
License: MIT
Platform: UNKNOWN
Requires-Dist: gitpython
Requires-Dist: jira
Requires-Dist: requests
